screensuite/__init__.py
screensuite/basebenchmark.py
screensuite/benchmark_result.py
screensuite/chat_message.py
screensuite/registry.py
screensuite/resize_image.py
screensuite/response_generation.py
screensuite/utils.py
screensuite/agents/__init__.py
screensuite/agents/models.py
screensuite/agents/prompt.py
screensuite/agents/qwentest.py
screensuite/agents/requirements.txt
screensuite/agents/run.py
screensuite/agents/client/android_env_client.py
screensuite/agents/client/desktop_env_client.py
screensuite/agents/client/osworld_vm_downloader.py
screensuite/agents/remote_env/__init__.py
screensuite/agents/remote_env/create_remote_env.py
screensuite/agents/remote_env/provider.py
screensuite/agents/remote_env/docker/provider.py
screensuite/agents/vision_agents/android_agent.py
screensuite/agents/vision_agents/base_vision_agent.py
screensuite/agents/vision_agents/desktop_agent.py
screensuite/agents/vision_agents/e2b_agent.py
screensuite/benchmarks/hubbasebenchmark.py
screensuite/benchmarks/model.py
screensuite/benchmarks/utils.py
screensuite/benchmarks/multistep/__init__.py
screensuite/benchmarks/multistep/config.py
screensuite/benchmarks/multistep/generation.py
screensuite/benchmarks/multistep/android_world/README.md
screensuite/benchmarks/multistep/android_world/__init__.py
screensuite/benchmarks/multistep/android_world/benchmark.py
screensuite/benchmarks/multistep/android_world/config.py
screensuite/benchmarks/multistep/android_world/make_hub_dataset.py
screensuite/benchmarks/multistep/android_world/task_metadata.json
screensuite/benchmarks/multistep/browse_comp/__init__.py
screensuite/benchmarks/multistep/browse_comp/benchmark.py
screensuite/benchmarks/multistep/browse_comp/config.py
screensuite/benchmarks/multistep/browse_comp/prompts.py
screensuite/benchmarks/multistep/browse_comp/tests/test_browse_comp.py
screensuite/benchmarks/multistep/gaia/__init__.py
screensuite/benchmarks/multistep/gaia/benchmark.py
screensuite/benchmarks/multistep/gaia/config.py
screensuite-0.0.1.dist-info/METADATA
screensuite-0.0.1.dist-info/WHEEL
screensuite-0.0.1.dist-info/licenses/LICENSE
screensuite-0.0.1.dist-info/RECORD
