Metadata-Version: 2.4
Name: screensuite
Version: 0.0.1
Summary: ScreenSuite
Author: Aymeric Roucher
Author-email: Amir Mahla <amir.mahla@huggingface.co>
License-File: LICENSE
Requires-Python: >=3.11
Requires-Dist: datasets>=3.5.0
Requires-Dist: e2b-desktop==1.7.1
Requires-Dist: joblib>=1.4.0
Requires-Dist: litellm
Requires-Dist: pillow>=11.0.0
Requires-Dist: protobuf<6.0.0.dev0,>=4.21.5
Requires-Dist: pydantic>=2.11.0
Requires-Dist: rouge>=1.0.1
Requires-Dist: smolagents[litellm,openai]>=1.15.0
Requires-Dist: torch>=2.6.0
Requires-Dist: torchvision>=0.21.0
Requires-Dist: tqdm>=4.67.0
Requires-Dist: transformers
Provides-Extra: android-world
Requires-Dist: android-world; extra == 'android-world'
Provides-Extra: dev
Requires-Dist: codespell>=2.3.0; extra == 'dev'
Requires-Dist: coverage>=7.6.4; extra == 'dev'
Requires-Dist: groq>=0.11.0; extra == 'dev'
Requires-Dist: ipdb>=0.13.13; extra == 'dev'
Requires-Dist: ipykernel>=6.29.5; extra == 'dev'
Requires-Dist: isort>=5.13.2; extra == 'dev'
Requires-Dist: matplotlib>=3.9.2; extra == 'dev'
Requires-Dist: mypy==1.14.1; extra == 'dev'
Requires-Dist: pip>=24.2; extra == 'dev'
Requires-Dist: pre-commit>=3.8.0; extra == 'dev'
Requires-Dist: pytest>=8.1.0; extra == 'dev'
Requires-Dist: ruff>=0.9.0; extra == 'dev'
Provides-Extra: osworld
Requires-Dist: osworld; extra == 'osworld'
Provides-Extra: submodules
Requires-Dist: android-world; extra == 'submodules'
Requires-Dist: osworld; extra == 'submodules'
